{
  "Objects": [
    {
      "Player.json": {
        "Transform": {
          "x": 0.0,
          "y": 0.0
        }
      }
    },
    {
      "Enemy.json": {
        "Transform": {
          "x": 0.5,
          "y": 0.5
        },
        "UpDown": "yes"
      }
    },
    {
      "Enemy.json": {
        "Transform": {
          "x": -0.5,
          "y": 0.5
        },
        "UpDown": "yes"
      }
    },
    {
      "Enemy.json": {
        "Transform": {
          "x": -0.5,
          "y": -0.5
        },
        "UpDown": "yes"
      }
    },
    {
      "Wall1.json": {
        "Transform": {
          "x": -1,
          "y": 0
        }
      }
    },
    {
      "Wall1.json": {
        "Transform": {
          "x": 1,
          "y": 0
        }
      }
    },
    {
      "Wall2.json": {
        "Transform": {
          "x": 0,
          "y": 1
        }
      }
    },
    {
      "Wall2.json": {
        "Transform": {
          "x": 0,
          "y": -1
        }
      }
    }
  ]

}